sxclzy/Dict.py
sxclzy/__init__.py
sxclzy/sqlite_model.py
sxclzy/sqlite_orm.py
sxclzy/sqlite_time_scheduling.py
sxclzy/sxclzy.py
sxclzy-0.2.3.dist-info/LICENSE
sxclzy-0.2.3.dist-info/METADATA
sxclzy-0.2.3.dist-info/WHEEL
sxclzy-0.2.3.dist-info/top_level.txt
sxclzy-0.2.3.dist-info/RECORD
