Metadata-Version: 2.1
Name: sxclzy
Version: 0.2.3
Summary: a tool to schedule your functions
Home-page: https://github.com/GuardianGH/sxclzy
Author: GuardianAngel
Author-email: zhling2012@live.com
License: UNKNOWN
Platform: UNKNOWN
Classifier: Programming Language :: Python :: 3
Classifier: License :: OSI Approved :: MIT License
Classifier: Operating System :: OS Independent
Requires-Dist: psutil (>=5.6.2)
Requires-Dist: prettytable (>=0.7.2)
Requires-Dist: SQLAlchemy (>=1.3.3)
Requires-Dist: dill (>=0.3.0)
